piko/__init__.py
piko/app.py
piko/compute/__init__.py
piko/compute/manager.py
piko/config/__init__.py
piko/config/defaults.toml
piko/core/__init__.py
piko/core/cache.py
piko/core/discovery.py
piko/core/registry.py
piko/core/resource.py
piko/core/runner.py
piko/core/scheduler.py
piko/core/types.py
piko/core/watcher.py
piko/infra/__init__.py
piko/infra/db.py
piko/infra/leader.py
piko/infra/logging.py
piko/infra/observability.py
piko/persistence/__init__.py
piko/persistence/intent.py
piko/persistence/sink_base.py
piko/persistence/writer.py
piko_cucc-0.1.8.dist-info/METADATA
piko_cucc-0.1.8.dist-info/WHEEL
piko_cucc-0.1.8.dist-info/licenses/LICENSE
piko_cucc-0.1.8.dist-info/RECORD
