Metadata-Version: 2.4
Name: piko-cucc
Version: 0.1.8
Summary: Data-Oriented Async Task Orchestrator
Project-URL: Homepage, https://github.com/yingsf/piko
Project-URL: Repository, https://github.com/yingsf/piko
Project-URL: Documentation, https://github.com/yingsf/piko/tree/dev#readme
Author-email: chenjp <chenjp105@x.com>
License: MIT
License-File: LICENSE
Keywords: asyncio,etl,framework,pipeline,scheduler
Classifier: Development Status :: 4 - Beta
Classifier: Framework :: AsyncIO
Classifier: Intended Audience :: Developers
Classifier: License :: OSI Approved :: MIT License
Classifier: Programming Language :: Python :: 3.12
Classifier: Topic :: Software Development :: Libraries :: Application Frameworks
Requires-Python: >=3.12
Requires-Dist: aiofiles>=25.1.0
Requires-Dist: apscheduler>=3.11.2
Requires-Dist: asyncmy>=0.2.10
Requires-Dist: cloudpickle>=3.1.2
Requires-Dist: croniter>=6.0.0
Requires-Dist: cryptography>=46.0.3
Requires-Dist: dynaconf>=3.2.12
Requires-Dist: fastapi>=0.128.0
Requires-Dist: greenlet>=3.0.0
Requires-Dist: prometheus-client>=0.23.1
Requires-Dist: pydantic>=2.12.5
Requires-Dist: sqlalchemy>=2.0.45
Requires-Dist: structlog>=25.5.0
Requires-Dist: uvicorn>=0.40.0
